[
  {
    "cover": "https://i0.hdslb.com/bfs/bangumi/b8e72ea69e57e0b7ac85d8b4d366554fd866df1a.jpg",
    "title": "OVERLORD",
    "link": "https://www.bilibili.com/bangumi/play/ss2576",
    "yearMonth": 201507
  },
  {
    "cover": "https://i0.hdslb.com/bfs/bangumi/image/40f364466f4214fbd12bd9bf6653295d92126409.png",
    "title": "干物妹！小埋",
    "link": "https://www.bilibili.com/bangumi/play/ss2580",
    "yearMonth": 201507
  },
  {
    "cover": "https://i0.hdslb.com/bfs/bangumi/9c3e77244687a81e4b75e88ec22eeb8dbaa26380.jpg",
    "title": "Charlotte",
    "link": "https://www.bilibili.com/bangumi/play/ss2572",
    "yearMonth": 201507
  },
  {
    "cover": "https://i0.hdslb.com/bfs/bangumi/08b4cc4bbef5c6ed8eff267201fbb1fbe3ef9faf.jpg",
    "title": "赤发白雪姬 第一季",
    "link": "https://www.bilibili.com/bangumi/play/ss2578",
    "yearMonth": 201507
  },
  {
    "cover": "https://i0.hdslb.com/bfs/bangumi/fe032695a01c4b04385306b9b2a5aed565e341cf.jpg",
    "title": "噬神者",
    "link": "https://www.bilibili.com/bangumi/play/ss2591",
    "yearMonth": 201507
  },
  {
    "cover": "https://i0.hdslb.com/bfs/bangumi/image/86b4b78cd908b30a26c772e6419de5d1385b1cb3.jpg",
    "title": "学园孤岛",
    "link": "https://www.bilibili.com/bangumi/play/ss2592",
    "yearMonth": 201507
  },
  {
    "cover": "https://i0.hdslb.com/bfs/bangumi/c2d4b22675f78f07d3b6562a0e336ac110cc35d7.jpg",
    "title": "空战魔导士候补生的教官",
    "link": "https://www.bilibili.com/bangumi/play/ss2583",
    "yearMonth": 201507
  },
  {
    "cover": "https://i0.hdslb.com/bfs/bangumi/7f403ac6bcacad8589e0976878541b7c3d2dc319.jpg",
    "title": "约会大作战 万由里裁决",
    "link": "https://www.bilibili.com/bangumi/play/ss5630?theme=movie",
    "yearMonth": 201507
  },
  {
    "cover": "https://i0.hdslb.com/bfs/bangumi/image/a40ab1fac72e7830eaebcbe978431921ec5bf668.png",
    "title": "艾克斯奥特曼",
    "link": "https://www.bilibili.com/bangumi/play/ss38410",
    "yearMonth": 201507
  },
  {
    "cover": "https://i0.hdslb.com/bfs/bangumi/e2044253dafb864962726cbae7ab07ab91f011ce.jpg",
    "title": "城下町的蒲公英",
    "link": "https://www.bilibili.com/bangumi/play/ss2613",
    "yearMonth": 201507
  },
  {
    "cover": "https://i0.hdslb.com/bfs/bangumi/84201f83b9bb22a5a541e194a8a160ca4ab291e5.jpg",
    "title": "无头骑士异闻录×2 转",
    "link": "https://www.bilibili.com/bangumi/play/ss2595",
    "yearMonth": 201507
  },
  {
    "cover": "https://i0.hdslb.com/bfs/bangumi/77ac5d140cc5079364536c5f630f05ca552a15cb.jpg",
    "title": "OVERLORD SP",
    "link": "https://www.bilibili.com/bangumi/play/ss3428",
    "yearMonth": 201507
  },
  {
    "cover": "https://i0.hdslb.com/bfs/bangumi/73409f75e23bd24eaf2db529f09ebb1150ec5c79.jpg",
    "title": "Charlotte SP",
    "link": "https://www.bilibili.com/bangumi/play/ss3429",
    "yearMonth": 201507
  },
  {
    "cover": "https://i0.hdslb.com/bfs/bangumi/f023cbe53828f0a9a8e4894f446d34427655b3fa.jpg",
    "title": "黑塔利亚 The World Twinkle 第6期",
    "link": "https://www.bilibili.com/bangumi/play/ss2581",
    "yearMonth": 201507
  },
  {
    "cover": "https://i0.hdslb.com/bfs/bangumi/260f63bd8dd23ca71a92c6453863d453d17ee55f.jpg",
    "title": "青春生存游戏",
    "link": "https://www.bilibili.com/bangumi/play/ss2589",
    "yearMonth": 201507
  },
  {
    "cover": "https://i0.hdslb.com/bfs/bangumi/2f8dca95dffdecc0e73b599b1f15ad170ebdebd5.jpg",
    "title": "迷糊餐厅 WORKING!!!",
    "link": "https://www.bilibili.com/bangumi/play/ss2587",
    "yearMonth": 201507
  },
  {
    "cover": "https://i0.hdslb.com/bfs/bangumi/image/78408bd068a63da81485b9703fe99d519a63acd5.jpg",
    "title": "Classroom☆Crisis",
    "link": "https://www.bilibili.com/bangumi/play/ss2582",
    "yearMonth": 201507
  },
  {
    "cover": "https://i0.hdslb.com/bfs/bangumi/b21d7dd79e574db51c38a7543b102fe7fac4acc5.jpg",
    "title": "和歌子酒 动画",
    "link": "https://www.bilibili.com/bangumi/play/ss2602",
    "yearMonth": 201507
  },
  {
    "cover": "https://i0.hdslb.com/bfs/bangumi/1ab702fd6fed6cc11d7152883491a471bf8dd155.jpg",
    "title": "那就是声优！",
    "link": "https://www.bilibili.com/bangumi/play/ss2588",
    "yearMonth": 201507
  },
  {
    "cover": "https://i0.hdslb.com/bfs/bangumi/10183cadf6a9bdd0b4ab3ea80cafe12a11140fe1.jpg",
    "title": "若叶女孩",
    "link": "https://www.bilibili.com/bangumi/play/ss2590",
    "yearMonth": 201507
  },
  {
    "cover": "https://i0.hdslb.com/bfs/bangumi/3ae9495a2e46af81f3d5c58066f5bff47e00b7c9.jpg",
    "title": "怪物之子",
    "link": "https://www.bilibili.com/bangumi/play/ss4129?theme=movie",
    "yearMonth": 201507
  },
  {
    "cover": "https://i0.hdslb.com/bfs/bangumi/b89d49818402aefc1244e43efb1220a2841e89bc.jpg",
    "title": "枕男子",
    "link": "https://www.bilibili.com/bangumi/play/ss2610",
    "yearMonth": 201507
  },
  {
    "cover": "https://i0.hdslb.com/bfs/bangumi/f1f65cbd78e20999b4dd3c5925ee907d869692ec.jpg",
    "title": "告白实行委员会 我于此刻恋上你",
    "link": "https://www.bilibili.com/bangumi/play/ss4140",
    "yearMonth": 201507
  },
  {
    "cover": "https://i0.hdslb.com/bfs/bangumi/435d113bda867a213864dc8ea2df97c0683a34df.jpg",
    "title": "排球少年剧场版 结束与开始",
    "link": "https://www.bilibili.com/bangumi/play/ss3542?theme=movie",
    "yearMonth": 201507
  },
  {
    "cover": "https://i0.hdslb.com/bfs/bangumi/170a15388a44a826c0e0afb4644b81fba981590a.jpg",
    "title": "偶像大师 灰姑娘女孩 第2期",
    "link": "https://www.bilibili.com/bangumi/play/ss2594",
    "yearMonth": 201507
  },
  {
    "cover": "https://i0.hdslb.com/bfs/bangumi/63c3f9ab3301bd26d9084fe048a372286d0ee210.jpg",
    "title": "黑白小姐 第二季",
    "link": "https://www.bilibili.com/bangumi/play/ss2617",
    "yearMonth": 201507
  },
  {
    "cover": "https://i0.hdslb.com/bfs/bangumi/545fd17a90d06ab762036b3634f484ccb7e4e71c.jpg",
    "title": "洲崎西 THE ANIMATION",
    "link": "https://www.bilibili.com/bangumi/play/ss2593",
    "yearMonth": 201507
  },
  {
    "cover": "https://i0.hdslb.com/bfs/bangumi/bfb6cd3b03c6dfabc543772895d36357c1e1352f.jpg",
    "title": "VENUS PROJECT -CLIMAX-",
    "link": "https://www.bilibili.com/bangumi/play/ss2599",
    "yearMonth": 201507
  },
  {
    "cover": "https://i0.hdslb.com/bfs/bangumi/fe032695a01c4b04385306b9b2a5aed565e341cf.jpg",
    "title": "噬神者 SP",
    "link": "https://www.bilibili.com/bangumi/play/ss3387",
    "yearMonth": 201507
  },
  {
    "cover": "https://i0.hdslb.com/bfs/bangumi/4579f7c65e7363a13dded966884d7e3af31800a6.jpg",
    "title": "科学小飞侠Crowds insight",
    "link": "https://www.bilibili.com/bangumi/play/ss2612",
    "yearMonth": 201507
  },
  {
    "cover": "https://i0.hdslb.com/bfs/bangumi/52c01669556664d73693ef56af7672cbb56f9f12.jpg",
    "title": "创圣的大天使LOGOS",
    "link": "https://www.bilibili.com/bangumi/play/ss2579",
    "yearMonth": 201507
  },
  {
    "cover": "https://i0.hdslb.com/bfs/bangumi/16de361f00e7481ee1ea65835a89c9c5909babe0.jpg",
    "title": "天体的秩序SP",
    "link": "https://www.bilibili.com/bangumi/play/ss5488",
    "yearMonth": 201507
  },
  {
    "cover": "https://i0.hdslb.com/bfs/bangumi/e7402dfc8ff4092dc723e45d40f8a3d1ba6469b9.jpg",
    "title": "百万偶像",
    "link": "https://www.bilibili.com/bangumi/play/ss2577",
    "yearMonth": 201507
  },
  {
    "cover": "https://i0.hdslb.com/bfs/bangumi/46298a922352cf277567fde26223275cbc8cb087.jpg",
    "title": "乌瑟的穷困生活 梦幻篇",
    "link": "https://www.bilibili.com/bangumi/play/ss2615",
    "yearMonth": 201507
  },
  {
    "cover": "https://i0.hdslb.com/bfs/bangumi/170a15388a44a826c0e0afb4644b81fba981590a.jpg",
    "title": "偶像大师 灰姑娘女孩 第二季 OVA",
    "link": "https://www.bilibili.com/bangumi/play/ss3788",
    "yearMonth": 201507
  },
  {
    "cover": "https://i0.hdslb.com/bfs/bangumi/393f610dc2736980efb559bcc352db33ebba3e6f.jpg",
    "title": "网球并不可笑嘛 第五季",
    "link": "https://www.bilibili.com/bangumi/play/ss2604",
    "yearMonth": 201507
  },
  {
    "cover": "https://i0.hdslb.com/bfs/bangumi/7a8e275cb301470288d1304e70625cd9d3e912c7.jpg",
    "title": "怪兽酒场干杯！",
    "link": "https://www.bilibili.com/bangumi/play/ss2608",
    "yearMonth": 201507
  },
  {
    "cover": "https://i0.hdslb.com/bfs/bangumi/d6bb008fcd05ba49ca33e239bd87748511c4eee5.jpg",
    "title": "故事少女穗乃花",
    "link": "https://www.bilibili.com/bangumi/play/ss4153",
    "yearMonth": 201507
  },
  {
    "cover": "https://i0.hdslb.com/bfs/bangumi/77d10f598a044ceb19c6baceed3852ff4c391312.jpg",
    "title": "面包超人：咪嘉和魔法神灯",
    "link": "https://www.bilibili.com/bangumi/play/ss4119?theme=movie",
    "yearMonth": 201507
  },
  {
    "cover": "https://i0.hdslb.com/bfs/bangumi/b4cb22784618e1bcb5f1b9b7e860f3cc950441bd.jpg",
    "title": "Peeping Life×怪兽酒场 怪兽们的所在之处",
    "link": "https://www.bilibili.com/bangumi/play/ss3912",
    "yearMonth": 201507
  },
  {
    "cover": "https://i0.hdslb.com/bfs/bangumi/17dd31be19a1e4e04cf74a123b28893dcef3fa72.jpg",
    "title": "香菜酱和她的亲人们",
    "link": "https://www.bilibili.com/bangumi/play/ss4117",
    "yearMonth": 201507
  }
]